blobcity/__init__.py
blobcity/aicloud/__init__.py
blobcity/aicloud/access_validation.py
blobcity/aicloud/auto_save_yaml.py
blobcity/code_gen/Generator.py
blobcity/code_gen/IpynbMeta.py
blobcity/code_gen/PyMeta.py
blobcity/code_gen/SourceCodes.py
blobcity/code_gen/__init__.py
blobcity/config/__init__.py
blobcity/config/classifier_config.py
blobcity/config/regressor_config.py
blobcity/config/time_config.py
blobcity/config/tuner.py
blobcity/image/__init__.py
blobcity/image/main/__init__.py
blobcity/image/main/driver.py
blobcity/main/__init__.py
blobcity/main/driver.py
blobcity/main/modelSelection.py
blobcity/store/DictClass.py
blobcity/store/Model.py
blobcity/store/__init__.py
blobcity/time/__init__.py
blobcity/time/main/__init__.py
blobcity/time/main/driver.py
blobcity/utils/AutoFeatureSelection.py
blobcity/utils/Cleaner.py
blobcity/utils/FileType.py
blobcity/utils/ProblemType.py
blobcity/utils/YamlGenerator.py
blobcity/utils/__init__.py
blobcity/utils/progress_bar.py
blobcity-0.0.13.dist-info/LICENSE
blobcity-0.0.13.dist-info/METADATA
blobcity-0.0.13.dist-info/WHEEL
blobcity-0.0.13.dist-info/top_level.txt
blobcity-0.0.13.dist-info/RECORD
