Metadata-Version: 2.1
Name: blobcity
Version: 0.0.13
Summary: Python based framework for Automatic AI for Regression and Classification over numerical data. Performs model search, hyper-parameter tuning, and high-quality Jupyter Notebook code generation.
Home-page: https://github.com/blobcity/autoai
Author: BlobCity, Inc
Author-email: support@blobcity.com
License: Apache License 2.0
Classifier: Programming Language :: Python :: 3.7
Classifier: Programming Language :: Python :: 3.8
Classifier: Programming Language :: Python :: 3.9
Classifier: License :: OSI Approved :: Apache Software License
Classifier: Operating System :: OS Independent
Requires-Python: >=3.6
License-File: LICENSE
Requires-Dist: dill (>=0.3.4)
Requires-Dist: cliff (>=3.6.0)
Requires-Dist: joblib (>=1.0.0)
Requires-Dist: nbformat (>=5.1.3)
Requires-Dist: requests (>=2.26.0)
Requires-Dist: numpy (>=1.21.0)
Requires-Dist: pandas (>=1.3.0)
Requires-Dist: httplib2 (>=0.20.0)
Requires-Dist: PyYAML (>=6.0)
Requires-Dist: scikit-learn (>=0.23.0)
Requires-Dist: seaborn (>=0.10.0)
Requires-Dist: optuna (>=2.6.0)
Requires-Dist: imbalanced-learn (>=0.8.0)
Requires-Dist: xgboost (>=1.4.0)
Requires-Dist: catboost (>=0.26)
Requires-Dist: lightgbm (>=3.2.0)
